{
"type": "FeatureCollection",
"name": "Trinkwasserstelle",
"crs": { "type": "name", "properties": { "name": "urn:ogc:def:crs:OGC:1.3:CRS84" } },
"features": [
{ "type": "Feature", "properties": { "osm_id": 303544486, "Beschränkung": "Kostenfrei", "amenity": "drinking_water", "natural": "spring", "fee": null, "man_made": null, "access": null, "covered": null, "drinking_water": null }, "geometry": { "type": "Point", "coordinates": [ 8.8300133, 49.390849699999968 ] } },
{ "type": "Feature", "properties": { "osm_id": 6680003135, "Beschränkung": "Kostenfrei", "amenity": "drinking_water", "natural": null, "fee": null, "man_made": null, "access": null, "covered": null, "drinking_water": null }, "geometry": { "type": "Point", "coordinates": [ 8.8394328, 49.379672899999989 ] } },
{ "type": "Feature", "properties": { "osm_id": 11887128564, "Beschränkung": "Kostenfrei", "amenity": "drinking_water", "natural": null, "fee": "no", "man_made": "water_tap", "access": null, "covered": null, "drinking_water": null }, "geometry": { "type": "Point", "coordinates": [ 8.8367772, 49.4054476 ] } },
{ "type": "Feature", "properties": { "osm_id": 11887136472, "Beschränkung": "Zahlungspflichtig", "amenity": "water_point", "natural": null, "fee": "yes", "man_made": null, "access": "customers", "covered": "no", "drinking_water": "yes" }, "geometry": { "type": "Point", "coordinates": [ 8.8365527, 49.4053422 ] } }
]
}
